bkmrk-0.2.1.dist-info/licenses/LICENSE
bm/__init__.py
bm/__main__.py
bm/cli.py
bm/commands.py
bm/io.py
bm/models.py
bm/utils.py
bkmrk-0.2.1.dist-info/METADATA
bkmrk-0.2.1.dist-info/WHEEL
bkmrk-0.2.1.dist-info/entry_points.txt
bkmrk-0.2.1.dist-info/top_level.txt
bkmrk-0.2.1.dist-info/RECORD
