Metadata-Version: 2.4
Name: bkmrk
Version: 0.2.1
Summary: Plain-text, pass-style bookmarks
License: MIT License
Keywords: bookmarks,bm,bkmrk,Plain-text bookmarks
Classifier: Programming Language :: Python :: 3
Classifier: License :: OSI Approved :: MIT License
Classifier: Operating System :: OS Independent
Requires-Python: >=3.8
License-File: LICENSE
Provides-Extra: dev
Requires-Dist: commitizen; extra == "dev"
Requires-Dist: pre-commit; extra == "dev"
Requires-Dist: pytest-cov; extra == "dev"
Requires-Dist: pytest>=7.0; extra == "dev"
Requires-Dist: ruff; extra == "dev"
Provides-Extra: build
Requires-Dist: build; extra == "build"
Requires-Dist: commitizen; extra == "build"
Requires-Dist: twine; extra == "build"
Dynamic: license-file
